transtokenizers/__init__.py
transtokenizers/transtokenizers.py
trans_tokenizers-0.1.4.dist-info/LICENSE
trans_tokenizers-0.1.4.dist-info/METADATA
trans_tokenizers-0.1.4.dist-info/WHEEL
trans_tokenizers-0.1.4.dist-info/top_level.txt
trans_tokenizers-0.1.4.dist-info/RECORD
