Metadata-Version: 2.2
Name: trans-tokenizers
Version: 0.1.4
Summary: Token translation for language models.
Author-email: Pieter Delobelle <pieter.delobelle@kuleuven.be>, François Remy <Francois.Remy@UGent.be>
License: MIT License
Project-URL: homepage, https://github.com/LAGoM-NLP/transtokenizer
Classifier: Development Status :: 2 - Pre-Alpha
Classifier: Intended Audience :: Developers
Classifier: License :: OSI Approved :: MIT License
Classifier: Natural Language :: English
Classifier: Programming Language :: Python :: 3
Classifier: Programming Language :: Python :: 3.9
License-File: LICENSE
Requires-Dist: torch>=1.9.0
Requires-Dist: transformers>=4.0.0
Requires-Dist: datasets>=1.0.0
Requires-Dist: tqdm>=4.60.0
Requires-Dist: numpy>=1.19.2
Requires-Dist: langcodes>=3.3.0
